tubed/__init__.py
tubed/main.py
tubed-0.2.1.dist-info/LICENSE
tubed-0.2.1.dist-info/METADATA
tubed-0.2.1.dist-info/WHEEL
tubed-0.2.1.dist-info/entry_points.txt
tubed-0.2.1.dist-info/RECORD
