Metadata-Version: 2.3
Name: tubed
Version: 0.2.1
Summary: Youtube downloader
License: MIT
Keywords: YouTube,download,downloader,tube,tubed,video,audio,mp3,mp4
Author: Mousa Zeid Baker
Requires-Python: >=3.9,<4.0
Classifier: Development Status :: 5 - Production/Stable
Classifier: License :: OSI Approved :: MIT License
Classifier: Operating System :: OS Independent
Classifier: Programming Language :: Python :: 3
Classifier: Programming Language :: Python :: 3.9
Classifier: Programming Language :: Python :: 3.10
Classifier: Programming Language :: Python :: 3.11
Classifier: Programming Language :: Python :: 3.12
Classifier: Programming Language :: Python :: 3.13
Requires-Dist: pytubefix (>=9.5.0,<10.0.0)
Requires-Dist: typer (>=0.17.4,<0.18.0)
Project-URL: Homepage, https://github.com/MousaZeidBaker/tubed
Project-URL: Repository, https://github.com/MousaZeidBaker/tubed
